setup.cfg
setup.py
marrow/__init__.py
marrow.script.egg-info/PKG-INFO
marrow.script.egg-info/SOURCES.txt
marrow.script.egg-info/dependency_links.txt
marrow.script.egg-info/namespace_packages.txt
marrow.script.egg-info/requires.txt
marrow.script.egg-info/top_level.txt
marrow.script.egg-info/zip-safe
marrow/script/__init__.py
marrow/script/core.py
marrow/script/release.py
marrow/script/util.py