Metadata-Version: 1.0
Name: marrow.script
Version: 2.0.0b1
Summary: Turn any callable into a powerful command line script through arglist introspection.
Home-page: https://github.com/marrow/marrow.script
Author: Alice Bevan-McGregor
Author-email: alice+marrow@gothcandy.com
License: MIT
Download-URL: http://pypi.python.org/pypi/marrow.script
Platform: UNKNOWN
Classifier: Development Status :: 4 - Beta
Classifier: Environment :: Console
Classifier: Intended Audience :: Developers
Classifier: License :: OSI Approved :: MIT License
Classifier: Operating System :: OS Independent
Classifier: Programming Language :: Python
Classifier: Programming Language :: Python :: 2.6
Classifier: Programming Language :: Python :: 2.7
Classifier: Programming Language :: Python :: 3
Classifier: Programming Language :: Python :: 3.1
Classifier: Programming Language :: Python :: 3.2
Classifier: Topic :: Software Development :: Libraries :: Python Modules
Classifier: Topic :: Utilities
